spamdetectorml/__init__.py
spamdetectorml/models/spam_detector_logit_model.pkl
spamdetectorml/models/spam_detector_nb_model.pkl
spamdetectorml/models/spam_detector_rf_model.pkl
spamdetectorml/models/spam_vectorizer.pkl
spamdetectorml/spamdetectorml.py
spamdetectorml-0.0.1.dist-info/WHEEL
spamdetectorml-0.0.1.dist-info/METADATA
spamdetectorml-0.0.1.dist-info/RECORD
