Metadata-Version: 2.1
Name: spamdetectorml
Version: 0.0.1
Summary: Classifying text as spam or not-spam using ML
Author: Author
Requires-Python: >=3.9,<4.0
Classifier: Programming Language :: Python :: 3
Classifier: Programming Language :: Python :: 3.10
Classifier: Programming Language :: Python :: 3.9
Requires-Dist: joblib (>=1.1.0,<2.0.0)
Requires-Dist: scikit-learn (>=1.0.2,<2.0.0)
